sopel_modules.birthdays-0.1.1-py3.7-nspkg.pth
sopel_modules/birthdays/__init__.py
sopel_modules/birthdays/birthdays.py
tests/__init__.py
tests/test_birthdays.py
sopel_modules.birthdays-0.1.1.dist-info/COPYING
sopel_modules.birthdays-0.1.1.dist-info/METADATA
sopel_modules.birthdays-0.1.1.dist-info/WHEEL
sopel_modules.birthdays-0.1.1.dist-info/namespace_packages.txt
sopel_modules.birthdays-0.1.1.dist-info/top_level.txt
sopel_modules.birthdays-0.1.1.dist-info/RECORD
