Metadata-Version: 2.1
Name: sopel-modules.birthdays
Version: 0.1.1
Summary: Print birthdays of notable people using wikipedia data
Home-page: https://github.com/shanedabes/sopel-birthdays
Author: Shane Donohoe
Author-email: shane@donohoe.cc
License: Eiffel Forum License, version 2
Platform: UNKNOWN
Requires-Dist: sopel (<7,>=6.0)
